pyassorted/__init__.py
pyassorted/asyncio/__init__.py
pyassorted/asyncio/executor.py
pyassorted/asyncio/io.py
pyassorted/asyncio/utils.py
pyassorted/cache/__init__.py
pyassorted/cache/cache.py
pyassorted/collections/__init__.py
pyassorted/collections/generator.py
pyassorted/collections/msg.py
pyassorted/collections/sqlitedict.py
pyassorted/datetime/__init__.py
pyassorted/datetime/datetime.py
pyassorted/datetime/timer.py
pyassorted/display/__init__.py
pyassorted/display/msg.py
pyassorted/display/obj.py
pyassorted/display/tb.py
pyassorted/encrypt/__init__.py
pyassorted/encrypt/io.py
pyassorted/fs/__init__.py
pyassorted/hardware/__init__.py
pyassorted/hardware/device.py
pyassorted/hash/__init__.py
pyassorted/hash/_string.py
pyassorted/http/__init__.py
pyassorted/http/socket.py
pyassorted/http/stream.py
pyassorted/io/__init__.py
pyassorted/io/watch.py
pyassorted/lock/__init__.py
pyassorted/lock/filelock.py
pyassorted/lock/key_lock.py
pyassorted/logger/__init__.py
pyassorted/logger/formatter.py
pyassorted/modules/__init__.py
pyassorted/modules/read.py
pyassorted/numerals/__init__.py
pyassorted/numerals/calculation.py
pyassorted/numerals/rand.py
pyassorted/rand/__init__.py
pyassorted/rand/_openai.py
pyassorted/rand/_string.py
pyassorted/standard/__init__.py
pyassorted/standard/language_code.py
pyassorted/string/__init__.py
pyassorted/string/find.py
pyassorted/string/rand.py
pyassorted/string/replace.py
pyassorted/string/validator.py
pyassorted/types/__init__.py
pyassorted/types/_inspect.py
pyassorted/types/_openai.py
pyassorted/types/_xml.py
pyassorted/types/casting.py
pyassorted/version.py
pyassorted/warn/__init__.py
pyassorted/warn/base.py
pyassorted-0.11.0.dist-info/LICENSE
pyassorted-0.11.0.dist-info/METADATA
pyassorted-0.11.0.dist-info/WHEEL
pyassorted-0.11.0.dist-info/RECORD
