Metadata-Version: 2.1
Name: pyassorted
Version: 0.11.0
Summary: A library has light-weight assorted utils in Prue-Python.
License: MIT
Author: Allen Chou
Author-email: f1470891079@gmail.com
Requires-Python: >=3.10.0,<4.0.0
Classifier: License :: OSI Approved :: MIT License
Classifier: Programming Language :: Python :: 3
Classifier: Programming Language :: Python :: 3.10
Classifier: Programming Language :: Python :: 3.11
Classifier: Programming Language :: Python :: 3.12
Requires-Dist: aiohttp
Requires-Dist: httpx
Requires-Dist: jinja2
Requires-Dist: numpy (>=2,<3)
Requires-Dist: pydantic-settings
Requires-Dist: pydantic[email,timezone] (>=2,<3)
Requires-Dist: pytz
Requires-Dist: rich
Requires-Dist: typing-extensions
